{"id": "nat1212", "name": "Midland Hills Country Club", "loc": [45.00274, -93.19741], "state": "Minnesota", "teeSets": [{"id": "nblack", "name": "Black", "rating": 73.7, "slope": 133}, {"id": "nblue", "name": "Blue", "rating": 71.9, "slope": 130}, {"id": "nbluewhit", "name": "Blue/White", "rating": 70.3, "slope": 128}, {"id": "nwhite", "name": "White", "rating": 68.4, "slope": 122}, {"id": "nwhitered", "name": "White/Red", "rating": 66.8, "slope": 118}, {"id": "nred", "name": "Red", "rating": 64.8, "slope": 114}, {"id": "nshort", "name": "Short", "rating": 60.2, "slope": 103}, {"id": "nbluew", "name": "Blue (W)", "rating": 78.1, "slope": 138}, {"id": "nbluewhitw", "name": "Blue/White (W)", "rating": 76.2, "slope": 135}, {"id": "nwhitew", "name": "White (W)", "rating": 73.9, "slope": 130}], "holes": [{"par": 4, "si": 13}, {"par": 4, "si": 7}, {"par": 4, "si": 3}, {"par": 3, "si": 17}, {"par": 4, "si": 1}, {"par": 5, "si": 9}, {"par": 3, "si": 15}, {"par": 4, "si": 5}, {"par": 4, "si": 11}, {"par": 5, "si": 12}, {"par": 4, "si": 4}, {"par": 3, "si": 10}, {"par": 4, "si": 8}, {"par": 4, "si": 2}, {"par": 4, "si": 18}, {"par": 3, "si": 14}, {"par": 5, "si": 6}, {"par": 4, "si": 16}], "tier": "gps", "geoUrl": "geo/nat/minnesota/1212.json", "nVerified": 16, "solved": false}