{"id": "nat1584", "name": "Bunker Hill Golf Course", "loc": [40.43595, -74.5755], "state": "New Jersey", "teeSets": [{"id": "nblue", "name": "Blue", "rating": 68.2, "slope": 118}, {"id": "nwhite", "name": "White", "rating": 67.2, "slope": 116}, {"id": "ngold", "name": "Gold", "rating": 63.3, "slope": 100}, {"id": "ngreen", "name": "Green", "rating": 60.5, "slope": 96}, {"id": "nbluew", "name": "Blue (W)", "rating": 73.2, "slope": 128}, {"id": "nwhitew", "name": "White (W)", "rating": 72.1, "slope": 126}, {"id": "ngoldw", "name": "Gold (W)", "rating": 67.4, "slope": 115}, {"id": "ngreenw", "name": "Green (W)", "rating": 63.1, "slope": 104}], "holes": [{"par": 4, "si": 7}, {"par": 4, "si": 15}, {"par": 5, "si": 1}, {"par": 3, "si": 17}, {"par": 4, "si": 11}, {"par": 3, "si": 5}, {"par": 5, "si": 9}, {"par": 4, "si": 13}, {"par": 4, "si": 3}, {"par": 4, "si": 4}, {"par": 4, "si": 16}, {"par": 5, "si": 8}, {"par": 3, "si": 6}, {"par": 4, "si": 10}, {"par": 3, "si": 18}, {"par": 4, "si": 12}, {"par": 4, "si": 14}, {"par": 5, "si": 2}], "tier": "gps", "geoUrl": "geo/nat/newjersey/1584.json", "nVerified": 17, "solved": false}