{"id": "nat11965", "name": "Turf Valley", "loc": [39.29676, -76.88332], "state": "Maryland", "teeSets": [{"id": "nblue", "name": "Blue", "rating": 73.3, "slope": 136}, {"id": "nbluewhit", "name": "Blue/White", "rating": 72.4, "slope": 133}, {"id": "nwhite", "name": "White", "rating": 71.6, "slope": 130}, {"id": "nwhitegol", "name": "White/Gold", "rating": 70.7, "slope": 128}, {"id": "ngold", "name": "Gold", "rating": 69.9, "slope": 122}, {"id": "nred", "name": "Red", "rating": 67.4, "slope": 116}, {"id": "nplatinum", "name": "Platinum", "rating": 61.8, "slope": 102}, {"id": "nmaroon", "name": "Maroon", "rating": 59.6, "slope": 98}, {"id": "nredw", "name": "Red (W)", "rating": 72, "slope": 131}, {"id": "nplatinumw", "name": "Platinum (W)", "rating": 64.2, "slope": 115}], "holes": [{"par": 5, "si": 9}, {"par": 4, "si": 3}, {"par": 3, "si": 15}, {"par": 4, "si": 5}, {"par": 4, "si": 7}, {"par": 4, "si": 1}, {"par": 4, "si": 11}, {"par": 3, "si": 13}, {"par": 5, "si": 17}, {"par": 4, "si": 6}, {"par": 4, "si": 14}, {"par": 4, "si": 8}, {"par": 3, "si": 16}, {"par": 5, "si": 18}, {"par": 4, "si": 2}, {"par": 4, "si": 12}, {"par": 3, "si": 10}, {"par": 4, "si": 4}], "tier": "gps", "geoUrl": "geo/nat/maryland/11965.json", "nVerified": 7, "solved": false}