{"id": "nat1457", "name": "Riviera Country Club", "loc": [34.04628, -118.5019], "state": "California", "teeSets": [{"id": "nblack", "name": "Black", "rating": 76.3, "slope": 144}, {"id": "nblue", "name": "Blue", "rating": 74.7, "slope": 139}, {"id": "nwhite", "name": "White", "rating": 72.4, "slope": 132}, {"id": "ngreen", "name": "Green", "rating": 70.6, "slope": 127}, {"id": "ngold", "name": "Gold", "rating": 68.7, "slope": 122}, {"id": "nred", "name": "Red", "rating": 67, "slope": 118}, {"id": "nblackw", "name": "Black (W)", "rating": 83.7, "slope": 155}, {"id": "nbluew", "name": "Blue (W)", "rating": 81.7, "slope": 151}, {"id": "nwhitew", "name": "White (W)", "rating": 78.8, "slope": 145}, {"id": "ngreenw", "name": "Green (W)", "rating": 76.7, "slope": 140}], "holes": [{"par": 5, "si": 17}, {"par": 4, "si": 1}, {"par": 4, "si": 7}, {"par": 3, "si": 9}, {"par": 4, "si": 5}, {"par": 3, "si": 15}, {"par": 4, "si": 11}, {"par": 4, "si": 13}, {"par": 4, "si": 3}, {"par": 4, "si": 16}, {"par": 5, "si": 10}, {"par": 4, "si": 8}, {"par": 4, "si": 6}, {"par": 3, "si": 18}, {"par": 4, "si": 2}, {"par": 3, "si": 14}, {"par": 5, "si": 12}, {"par": 4, "si": 4}], "tier": "gps", "geoUrl": "geo/nat/ca/1457.json", "nVerified": 16, "solved": false}