{"id": "nat11588", "name": "Voyager Village Par 3", "loc": [45.95839, -92.15373], "state": "Wisconsin", "teeSets": [{"id": "nblack", "name": "Black", "rating": 72.7, "slope": 131}, {"id": "nblue", "name": "Blue", "rating": 71.3, "slope": 128}, {"id": "nbluesilv", "name": "Blue-Silver", "rating": 70.8, "slope": 126}, {"id": "nsilver", "name": "Silver", "rating": 69.3, "slope": 121}, {"id": "nsilvergo", "name": "Silver/Gold", "rating": 67.9, "slope": 119}, {"id": "ngold", "name": "Gold", "rating": 66.2, "slope": 113}, {"id": "ngoldteal", "name": "Gold/Teal", "rating": 62.7, "slope": 100}, {"id": "nteal", "name": "Teal", "rating": 59.6, "slope": 89}, {"id": "nsilverw", "name": "Silver (W)", "rating": 75.2, "slope": 131}, {"id": "nsilvergow", "name": "Silver/Gold (W)", "rating": 73.3, "slope": 124}], "holes": [{"par": 4, "si": 13}, {"par": 5, "si": 3}, {"par": 4, "si": 7}, {"par": 3, "si": 15}, {"par": 4, "si": 9}, {"par": 5, "si": 1}, {"par": 4, "si": 11}, {"par": 3, "si": 17}, {"par": 4, "si": 5}], "tier": "card", "geoUrl": null, "nVerified": 2, "solved": false}