{"id": "nat10548", "name": "Lake Forest Golf Course", "loc": [30.64749, -87.88833], "state": "Alabama", "teeSets": [{"id": "nblue2023", "name": "Blue 2023", "rating": 71, "slope": 123}, {"id": "nwhite202", "name": "White 2023", "rating": 69.6, "slope": 118}, {"id": "nwhitegre", "name": "White / Green 2023", "rating": 68, "slope": 112}, {"id": "ngreen202", "name": "Green 2023", "rating": 66.9, "slope": 111}, {"id": "nred2023", "name": "Red 2023", "rating": 64.8, "slope": 107}, {"id": "nred2023w", "name": "Red 2023 (W)", "rating": 69.6, "slope": 112}, {"id": "ngold2023w", "name": "Gold 2023 (W)", "rating": 68.6, "slope": 111}], "holes": [{"par": 5, "si": 17}, {"par": 4, "si": 11}, {"par": 4, "si": 5}, {"par": 3, "si": 13}, {"par": 4, "si": 1}, {"par": 4, "si": 3}, {"par": 4, "si": 15}, {"par": 5, "si": 9}, {"par": 3, "si": 7}, {"par": 4, "si": 6}, {"par": 4, "si": 18}, {"par": 5, "si": 12}, {"par": 3, "si": 16}, {"par": 5, "si": 10}, {"par": 4, "si": 4}, {"par": 4, "si": 2}, {"par": 3, "si": 14}, {"par": 4, "si": 8}], "tier": "gps", "geoUrl": "geo/nat/alabama/10548.json", "nVerified": 17, "solved": false}