{"id": "nat11244", "name": "Fairways of Woodside", "loc": [43.16892, -88.2139], "state": "Wisconsin", "teeSets": [{"id": "nblack", "name": "Black", "rating": 71.3, "slope": 127}, {"id": "nmember", "name": "Member", "rating": 69.8, "slope": 125}, {"id": "nwhite", "name": "White", "rating": 68.7, "slope": 123}, {"id": "ncombo", "name": "Combo", "rating": 64.7, "slope": 115}, {"id": "nred", "name": "Red", "rating": 63.9, "slope": 113}, {"id": "nwhitew", "name": "White (W)", "rating": 73.9, "slope": 129}, {"id": "ncombow", "name": "Combo (W)", "rating": 69, "slope": 119}, {"id": "nredw", "name": "Red (W)", "rating": 68, "slope": 117}], "holes": [{"par": 4, "si": 18}, {"par": 4, "si": 8}, {"par": 3, "si": 6}, {"par": 4, "si": 12}, {"par": 4, "si": 16}, {"par": 4, "si": 10}, {"par": 4, "si": 4}, {"par": 3, "si": 14}, {"par": 5, "si": 2}, {"par": 4, "si": 9}, {"par": 4, "si": 11}, {"par": 3, "si": 15}, {"par": 5, "si": 3}, {"par": 4, "si": 7}, {"par": 5, "si": 1}, {"par": 3, "si": 17}, {"par": 4, "si": 5}, {"par": 4, "si": 13}], "tier": "gps", "geoUrl": "geo/nat/wisconsin/11244.json", "nVerified": 18, "solved": false}