{"id": "nat2507", "name": "Pheasant Run Golf Club", "loc": [42.29633, -83.50367], "state": "Michigan", "teeSets": [{"id": "ngold", "name": "GOLD", "rating": 74.4, "slope": 141}, {"id": "nblack", "name": "BLACK", "rating": 71.9, "slope": 137}, {"id": "nwhite", "name": "WHITE", "rating": 69.1, "slope": 128}, {"id": "nwhitegre", "name": "WHITE/GREEN", "rating": 66.9, "slope": 121}, {"id": "ngreen", "name": "GREEN", "rating": 64.9, "slope": 112}, {"id": "nwhitew", "name": "WHITE (W)", "rating": 75.3, "slope": 143}, {"id": "nwhitegrew", "name": "WHITE/GREEN (W)", "rating": 72.3, "slope": 134}, {"id": "ngreenw", "name": "GREEN (W)", "rating": 70.2, "slope": 126}], "holes": [{"par": 4, "si": 9}, {"par": 5, "si": 7}, {"par": 4, "si": 11}, {"par": 4, "si": 3}, {"par": 3, "si": 15}, {"par": 4, "si": 13}, {"par": 3, "si": 17}, {"par": 4, "si": 1}, {"par": 5, "si": 5}, {"par": 4, "si": 12}, {"par": 4, "si": 14}, {"par": 4, "si": 2}, {"par": 5, "si": 4}, {"par": 3, "si": 18}, {"par": 4, "si": 10}, {"par": 3, "si": 16}, {"par": 4, "si": 6}, {"par": 5, "si": 8}], "tier": "gps", "geoUrl": "geo/nat/mi/2507.json", "nVerified": 8, "solved": false}