{"id": "nat2189", "name": "The Practice Center - Clear Creek", "loc": [39.54864, -84.29337], "state": "Ohio", "teeSets": [{"id": "npbdye", "name": "PB Dye", "rating": 57.4, "slope": 85}, {"id": "nblack", "name": "Black", "rating": 54.8, "slope": 80}, {"id": "nblue", "name": "Blue", "rating": 53.4, "slope": 77}, {"id": "nred", "name": "Red", "rating": 51, "slope": 72}, {"id": "npbdyew", "name": "PB Dye (W)", "rating": 57.8, "slope": 87}, {"id": "nblackw", "name": "Black (W)", "rating": 56.9, "slope": 85}, {"id": "nbluew", "name": "Blue (W)", "rating": 55.4, "slope": 83}, {"id": "nredw", "name": "Red (W)", "rating": 53.3, "slope": 79}], "holes": [{"par": 3, "si": 9}, {"par": 3, "si": 3}, {"par": 3, "si": 1}, {"par": 3, "si": 5}, {"par": 4, "si": 7}, {"par": 3, "si": 15}, {"par": 3, "si": 11}, {"par": 3, "si": 13}, {"par": 3, "si": 17}, {"par": 3, "si": 8}, {"par": 3, "si": 16}, {"par": 3, "si": 4}, {"par": 3, "si": 14}, {"par": 4, "si": 6}, {"par": 3, "si": 10}, {"par": 3, "si": 12}, {"par": 3, "si": 2}, {"par": 3, "si": 18}], "tier": "gps", "geoUrl": "geo/nat/oh/2189.json", "nVerified": 15, "solved": false}