{"id": "nat3646", "name": "Shoal Creek Golf Course", "loc": [39.25212, -94.47908], "state": "Missouri", "teeSets": [{"id": "ngold", "name": "Gold", "rating": 74.1, "slope": 140}, {"id": "ngoldblue", "name": "Gold/Blue", "rating": 72.5, "slope": 136}, {"id": "nblue", "name": "Blue", "rating": 70.5, "slope": 128}, {"id": "nbluewhit", "name": "Blue/White", "rating": 69, "slope": 125}, {"id": "nwhite", "name": "White", "rating": 67.1, "slope": 120}, {"id": "nwhitebla", "name": "White/Black", "rating": 65.7, "slope": 117}, {"id": "nblack", "name": "Black", "rating": 63.2, "slope": 109}, {"id": "nbluew", "name": "Blue (W)", "rating": 77.3, "slope": 143}, {"id": "nbluewhitw", "name": "Blue/White (W)", "rating": 75.1, "slope": 138}, {"id": "nwhitew", "name": "White (W)", "rating": 72.7, "slope": 136}], "holes": [{"par": 4, "si": 3}, {"par": 4, "si": 15}, {"par": 3, "si": 13}, {"par": 4, "si": 7}, {"par": 3, "si": 11}, {"par": 4, "si": 17}, {"par": 5, "si": 1}, {"par": 4, "si": 5}, {"par": 5, "si": 9}, {"par": 4, "si": 10}, {"par": 3, "si": 14}, {"par": 4, "si": 16}, {"par": 5, "si": 4}, {"par": 4, "si": 6}, {"par": 4, "si": 8}, {"par": 4, "si": 18}, {"par": 3, "si": 12}, {"par": 4, "si": 2}], "tier": "gps", "geoUrl": "geo/nat/missouri/3646.json", "nVerified": 16, "solved": false}