{"id": "nat3157", "name": "Stillwater Country Club", "loc": [45.07193, -92.81931], "state": "Minnesota", "teeSets": [{"id": "nblue", "name": "Blue", "rating": 72.5, "slope": 135}, {"id": "nbluewhit", "name": "Blue/White", "rating": 71.8, "slope": 134}, {"id": "nwhite", "name": "White", "rating": 70.9, "slope": 132}, {"id": "nwhitegol", "name": "White/Gold", "rating": 68.6, "slope": 128}, {"id": "ngold", "name": "Gold", "rating": 66.9, "slope": 121}, {"id": "ngoldred", "name": "Gold/Red", "rating": 66, "slope": 119}, {"id": "nred", "name": "Red", "rating": 65.1, "slope": 117}, {"id": "nredpurpl", "name": "Red/Purple", "rating": 63.5, "slope": 114}, {"id": "npurple", "name": "Purple", "rating": 62, "slope": 111}, {"id": "nbluew", "name": "Blue (W)", "rating": 78.8, "slope": 139}], "holes": [{"par": 4, "si": 7}, {"par": 4, "si": 9}, {"par": 4, "si": 11}, {"par": 4, "si": 1}, {"par": 5, "si": 13}, {"par": 4, "si": 5}, {"par": 4, "si": 17}, {"par": 3, "si": 15}, {"par": 4, "si": 3}, {"par": 4, "si": 4}, {"par": 5, "si": 16}, {"par": 4, "si": 12}, {"par": 3, "si": 10}, {"par": 4, "si": 6}, {"par": 4, "si": 2}, {"par": 4, "si": 8}, {"par": 3, "si": 14}, {"par": 5, "si": 18}], "tier": "gps", "geoUrl": "geo/nat/minnesota/3157.json", "nVerified": 16, "solved": false}