{"id": "nat3171", "name": "Brookledge Golf Course", "loc": [41.12758, -81.45635], "state": "Ohio", "teeSets": [{"id": "nblack", "name": "Black", "rating": 71.3, "slope": 133}, {"id": "nblackblu", "name": "Black / Blue", "rating": 70.2, "slope": 132}, {"id": "nblue", "name": "Blue", "rating": 68.4, "slope": 132}, {"id": "nbluewhit", "name": "Blue / White", "rating": 67.4, "slope": 128}, {"id": "nwhite", "name": "White", "rating": 66.8, "slope": 119}, {"id": "nyelloww", "name": "Yellow (W)", "rating": 68.4, "slope": 124}], "holes": [{"par": 5, "si": 12}, {"par": 4, "si": 4}, {"par": 4, "si": 14}, {"par": 3, "si": 18}, {"par": 4, "si": 8}, {"par": 3, "si": 16}, {"par": 5, "si": 6}, {"par": 3, "si": 10}, {"par": 4, "si": 2}, {"par": 4, "si": 9}, {"par": 5, "si": 5}, {"par": 3, "si": 7}, {"par": 4, "si": 17}, {"par": 3, "si": 13}, {"par": 4, "si": 1}, {"par": 5, "si": 3}, {"par": 4, "si": 11}, {"par": 4, "si": 15}], "tier": "gps", "geoUrl": "geo/nat/oh/3171.json", "nVerified": 18, "solved": false}