{"id": "nat4309", "name": "Green Lea Golf Course", "loc": [43.66863, -93.36739], "state": "Minnesota", "teeSets": [{"id": "nblue", "name": "Blue", "rating": 69.9, "slope": 117}, {"id": "nwhite", "name": "White", "rating": 68.9, "slope": 115}, {"id": "ngold", "name": "Gold", "rating": 64.9, "slope": 108}, {"id": "nwhitew", "name": "White (W)", "rating": 74.2, "slope": 126}, {"id": "ngoldw", "name": "Gold (W)", "rating": 69.3, "slope": 117}, {"id": "nredw", "name": "Red (W)", "rating": 68.9, "slope": 116}], "holes": [{"par": 4, "si": 3}, {"par": 3, "si": 11}, {"par": 5, "si": 9}, {"par": 4, "si": 13}, {"par": 4, "si": 7}, {"par": 4, "si": 1}, {"par": 4, "si": 15}, {"par": 3, "si": 17}, {"par": 4, "si": 5}, {"par": 5, "si": 4}, {"par": 5, "si": 10}, {"par": 4, "si": 18}, {"par": 3, "si": 14}, {"par": 4, "si": 16}, {"par": 3, "si": 12}, {"par": 4, "si": 8}, {"par": 5, "si": 6}, {"par": 4, "si": 2}], "tier": "gps", "geoUrl": "geo/nat/minnesota/4309.json", "nVerified": 16, "solved": false}