{"id": "nat458", "name": "Black Swan Country Club", "loc": [42.71421, -71.01096], "state": "Massachusetts", "teeSets": [{"id": "nblack", "name": "BLACK", "rating": 72.9, "slope": 130}, {"id": "nblue", "name": "BLUE", "rating": 71, "slope": 126}, {"id": "nbluewhit", "name": "BLUE/WHITE COMBO", "rating": 70.4, "slope": 123}, {"id": "nwhite", "name": "WHITE", "rating": 69, "slope": 116}, {"id": "nred", "name": "RED", "rating": 64.6, "slope": 113}, {"id": "nwhitew", "name": "WHITE (W)", "rating": 74, "slope": 132}, {"id": "nredw", "name": "RED (W)", "rating": 70.6, "slope": 121}], "holes": [{"par": 4, "si": 7}, {"par": 5, "si": 11}, {"par": 3, "si": 9}, {"par": 5, "si": 3}, {"par": 4, "si": 15}, {"par": 3, "si": 17}, {"par": 4, "si": 13}, {"par": 4, "si": 5}, {"par": 4, "si": 1}, {"par": 4, "si": 8}, {"par": 4, "si": 16}, {"par": 3, "si": 14}, {"par": 5, "si": 4}, {"par": 4, "si": 12}, {"par": 4, "si": 2}, {"par": 4, "si": 6}, {"par": 3, "si": 18}, {"par": 5, "si": 10}], "tier": "gps", "geoUrl": "geo/nat/massachusett/458.json", "nVerified": 17, "solved": false}