{"id": "nat6789", "name": "Mercer County Elks Golf Club", "loc": [40.44362, -84.56653], "state": "Ohio", "teeSets": [{"id": "ngold", "name": "Gold", "rating": 71.6, "slope": 126}, {"id": "nbluegold", "name": "Blue-Gold", "rating": 70.6, "slope": 125}, {"id": "nblue", "name": "Blue", "rating": 69.5, "slope": 124}, {"id": "nbluegree", "name": "Blue-Green", "rating": 67.3, "slope": 120}, {"id": "ngreen", "name": "Green", "rating": 66, "slope": 117}, {"id": "nwhite", "name": "White", "rating": 64, "slope": 112}, {"id": "ngreenw", "name": "Green (W)", "rating": 71.5, "slope": 118}, {"id": "nwhitew", "name": "White (W)", "rating": 69, "slope": 116}], "holes": [{"par": 5, "si": 15}, {"par": 3, "si": 13}, {"par": 4, "si": 5}, {"par": 4, "si": 1}, {"par": 3, "si": 11}, {"par": 4, "si": 9}, {"par": 4, "si": 7}, {"par": 5, "si": 3}, {"par": 4, "si": 17}, {"par": 4, "si": 14}, {"par": 4, "si": 6}, {"par": 4, "si": 8}, {"par": 5, "si": 12}, {"par": 4, "si": 2}, {"par": 4, "si": 18}, {"par": 3, "si": 16}, {"par": 4, "si": 10}, {"par": 4, "si": 4}], "tier": "card", "geoUrl": null, "nVerified": 3, "solved": false}