{"id": "nat6368", "name": "Fairlawn Golf Course", "loc": [44.05144, -70.33477], "state": "Maine", "teeSets": [{"id": "nblack", "name": "BLACK", "rating": 71.5, "slope": 124}, {"id": "nwhite", "name": "WHITE", "rating": 70.5, "slope": 123}, {"id": "ntourname", "name": "TOURNAMENT", "rating": 68.7, "slope": 121}, {"id": "ngold", "name": "GOLD", "rating": 68, "slope": 118}, {"id": "nred", "name": "RED", "rating": 63.6, "slope": 106}, {"id": "nwhitew", "name": "White (W)", "rating": 77.1, "slope": 135}, {"id": "ntournamew", "name": "Tournament (W)", "rating": 74.8, "slope": 129}, {"id": "ngoldw", "name": "Gold (W)", "rating": 73.8, "slope": 123}, {"id": "nredw", "name": "Red (W)", "rating": 67.4, "slope": 117}], "holes": [{"par": 4, "si": 15}, {"par": 3, "si": 7}, {"par": 5, "si": 9}, {"par": 4, "si": 1}, {"par": 4, "si": 5}, {"par": 4, "si": 3}, {"par": 5, "si": 13}, {"par": 3, "si": 11}, {"par": 4, "si": 17}, {"par": 4, "si": 2}, {"par": 3, "si": 18}, {"par": 5, "si": 14}, {"par": 3, "si": 12}, {"par": 4, "si": 8}, {"par": 4, "si": 4}, {"par": 5, "si": 10}, {"par": 4, "si": 6}, {"par": 4, "si": 16}], "tier": "gps", "geoUrl": "geo/nat/maine/6368.json", "nVerified": 18, "solved": false}