{"id": "nat7416", "name": "St. Cloud Country Club", "loc": [45.51908, -94.14846], "state": "Minnesota", "teeSets": [{"id": "nblack", "name": "Black", "rating": 72.7, "slope": 134}, {"id": "nwhite", "name": "White", "rating": 71.6, "slope": 133}, {"id": "ngreen", "name": "Green", "rating": 69.6, "slope": 128}, {"id": "nyellow", "name": "Yellow", "rating": 67.8, "slope": 121}, {"id": "nlightblu", "name": "Light Blue", "rating": 66, "slope": 116}, {"id": "nforward", "name": "Forward", "rating": 61.6, "slope": 108}, {"id": "ngreenw", "name": "Green (W)", "rating": 74.5, "slope": 131}, {"id": "nyelloww", "name": "Yellow (W)", "rating": 72.4, "slope": 127}, {"id": "nlightbluw", "name": "Light Blue (W)", "rating": 70.2, "slope": 122}, {"id": "nlightbluw2", "name": "Light Blue/Forward Combo (W)", "rating": 65.9, "slope": 113}], "holes": [{"par": 4, "si": 3}, {"par": 4, "si": 7}, {"par": 3, "si": 13}, {"par": 5, "si": 17}, {"par": 4, "si": 1}, {"par": 3, "si": 15}, {"par": 4, "si": 5}, {"par": 4, "si": 9}, {"par": 5, "si": 11}, {"par": 5, "si": 16}, {"par": 4, "si": 14}, {"par": 3, "si": 6}, {"par": 4, "si": 2}, {"par": 4, "si": 10}, {"par": 5, "si": 18}, {"par": 3, "si": 8}, {"par": 4, "si": 12}, {"par": 4, "si": 4}], "tier": "gps", "geoUrl": "geo/nat/minnesota/7416.json", "nVerified": 18, "solved": false}