{"id": "nat8120", "name": "Apple Valley Golf Club", "loc": [40.44607, -82.35958], "state": "Ohio", "teeSets": [{"id": "nblack", "name": "Black", "rating": 73.4, "slope": 128}, {"id": "nblue", "name": "Blue", "rating": 71.4, "slope": 124}, {"id": "nwhite", "name": "White", "rating": 69.3, "slope": 122}, {"id": "ncombowhi", "name": "Combo White/Gold", "rating": 67, "slope": 114}, {"id": "ngold", "name": "Gold", "rating": 64.7, "slope": 110}, {"id": "nwhitew", "name": "White (W)", "rating": 75.4, "slope": 127}, {"id": "ncombowhiw", "name": "Combo White/Gold (W)", "rating": 72.4, "slope": 124}, {"id": "ngoldw", "name": "Gold (W)", "rating": 69.2, "slope": 118}], "holes": [{"par": 4, "si": 3}, {"par": 4, "si": 15}, {"par": 5, "si": 9}, {"par": 4, "si": 17}, {"par": 3, "si": 13}, {"par": 5, "si": 7}, {"par": 3, "si": 5}, {"par": 4, "si": 1}, {"par": 4, "si": 11}, {"par": 5, "si": 10}, {"par": 4, "si": 6}, {"par": 5, "si": 8}, {"par": 3, "si": 12}, {"par": 4, "si": 4}, {"par": 4, "si": 2}, {"par": 3, "si": 18}, {"par": 4, "si": 16}, {"par": 4, "si": 14}], "tier": "gps", "geoUrl": "geo/nat/oh/8120.json", "nVerified": 18, "solved": false}