{"id": "nat8463", "name": "Sagamore-Hampton Golf Club", "loc": [42.99391, -70.84066], "state": "New Hampshire", "teeSets": [{"id": "nblack", "name": "Black", "rating": 67.8, "slope": 116}, {"id": "ngreen", "name": "Green", "rating": 66.5, "slope": 112}, {"id": "nsilver", "name": "Silver", "rating": 61.8, "slope": 102}, {"id": "nblackw", "name": "Black (W)", "rating": 73.2, "slope": 122}, {"id": "ngreenw", "name": "Green (W)", "rating": 71.4, "slope": 119}, {"id": "nsilverw", "name": "Silver (W)", "rating": 65.6, "slope": 107}], "holes": [{"par": 4, "si": 18}, {"par": 4, "si": 6}, {"par": 4, "si": 4}, {"par": 3, "si": 16}, {"par": 4, "si": 14}, {"par": 5, "si": 12}, {"par": 3, "si": 2}, {"par": 5, "si": 8}, {"par": 3, "si": 10}, {"par": 5, "si": 9}, {"par": 3, "si": 5}, {"par": 4, "si": 3}, {"par": 5, "si": 13}, {"par": 3, "si": 15}, {"par": 4, "si": 17}, {"par": 5, "si": 11}, {"par": 3, "si": 7}, {"par": 4, "si": 1}], "tier": "gps", "geoUrl": "geo/nat/newhampshire/8463.json", "nVerified": 18, "solved": false}