{"id": "nat9173", "name": "Wilkes-Barre Golf Club", "loc": [41.18906, -75.80392], "state": "Pennsylvania", "teeSets": [{"id": "nblue", "name": "Blue", "rating": 73.6, "slope": 133}, {"id": "nwhite", "name": "White", "rating": 71.8, "slope": 130}, {"id": "ngold", "name": "Gold", "rating": 69.7, "slope": 126}, {"id": "nredw", "name": "Red (W)", "rating": 69.8, "slope": 121}], "holes": [{"par": 4, "si": 1}, {"par": 5, "si": 3}, {"par": 4, "si": 5}, {"par": 3, "si": 7}, {"par": 5, "si": 9}, {"par": 4, "si": 11}, {"par": 3, "si": 13}, {"par": 4, "si": 15}, {"par": 4, "si": 17}, {"par": 5, "si": 2}, {"par": 4, "si": 4}, {"par": 3, "si": 6}, {"par": 4, "si": 8}, {"par": 4, "si": 10}, {"par": 4, "si": 12}, {"par": 5, "si": 14}, {"par": 3, "si": 16}, {"par": 4, "si": 18}], "tier": "card", "geoUrl": null, "nVerified": 0, "solved": false}