{"id": "nat9880", "name": "Princeville Makai Golf Club", "loc": [22.2214, -159.48252], "state": "Hawaii", "teeSets": [{"id": "nainagree", "name": "Aina(Green)", "rating": 75.4, "slope": 134}, {"id": "nkoacombi", "name": "Koa (Combination)", "rating": 71.8, "slope": 131}, {"id": "nkaiocean", "name": "Kai(Ocean Blue)", "rating": 71.6, "slope": 129}, {"id": "nahiyello", "name": "AHI(Yellow)", "rating": 69.7, "slope": 127}, {"id": "nlaniskyb", "name": "LANI(Sky Blue)", "rating": 67, "slope": 119}, {"id": "nkaupualb", "name": "Ka'upu Albatross", "rating": 64.6, "slope": 108}, {"id": "nainagreew", "name": "Aina (Green ) (W)", "rating": 83, "slope": 151}, {"id": "nkoacombiw", "name": "Koa (Combination) (W)", "rating": 79.3, "slope": 143}, {"id": "nkaioceanw", "name": "Kai (Ocean Blue) (W)", "rating": 79.1, "slope": 136}, {"id": "nahiyellow", "name": "Ahi (Yellow) (W)", "rating": 76.5, "slope": 135}], "holes": [{"par": 4, "si": 13}, {"par": 5, "si": 9}, {"par": 3, "si": 15}, {"par": 4, "si": 1}, {"par": 5, "si": 11}, {"par": 4, "si": 3}, {"par": 3, "si": 7}, {"par": 4, "si": 17}, {"par": 4, "si": 5}, {"par": 4, "si": 6}, {"par": 5, "si": 14}, {"par": 4, "si": 4}, {"par": 3, "si": 8}, {"par": 4, "si": 18}, {"par": 4, "si": 16}, {"par": 3, "si": 12}, {"par": 4, "si": 2}, {"par": 5, "si": 10}], "tier": "gps", "geoUrl": "geo/nat/hawaii/9880.json", "nVerified": 14, "solved": false}